{
    "db": {
        "url": "mongodb://93.188.167.68:33017",
        "database": "letsPlay"
    },
    "app": {
        "url": "http://93.188.167.68",
        "port": 6700
    },
    "webServer": {
        "url": "http://93.188.167.68/",
        "port": 6700
    },
    "auth": {
        "jwtKey": "supersecret"
    },
    "image": {
        "url": "http://93.188.167.68/projects/lets-play_nodejs/",
        "port": 6700
    },
    "providers": {},
    "logger": {
        "logStart": false,
        "file": {
            "filename": "logs/logs.json",
            "level": "silly",
            "handleExceptions": true,
            "json": true,
            "maxsize": 512000,
            "maxFiles": 5,
            "colorize": false
        },
        "console": {
            "level": "debug",
            "handleExceptions": true,
            "json": false,
            "colorize": true
        },
        "http": {}
    }
}